roles/__init__.py
roles/context.py
roles/django.py
roles/factory.py
roles/role.py
py_roles-0.1.dist-info/METADATA
py_roles-0.1.dist-info/WHEEL
py_roles-0.1.dist-info/top_level.txt
py_roles-0.1.dist-info/RECORD
