Metadata-Version: 2.1
Name: py-roles
Version: 0.1
Summary: Role based development
Home-page: UNKNOWN
Author: Leonid Soputnyak
Author-email: leonid.soputnyak@gmail.com
License: BSD License
Keywords: role DCI data context interaction
Platform: All
Classifier: Development Status :: 4 - Beta
Classifier: Intended Audience :: Developers
Classifier: License :: OSI Approved :: BSD License
Classifier: Natural Language :: English
Classifier: Operating System :: OS Independent
Classifier: Programming Language :: Python :: 3
Classifier: Programming Language :: Python :: 3.7
Classifier: Topic :: Software Development :: Libraries
